Workbook

Sheet Assumptions
A1: JS Contracting & Electrical Services: financial model assumptions
A2: Blue cells are inputs; yellow cells are the key levers. Black cells are formulas. Every other sheet is driven from here. Month 1 is the first month of operations.
A3: Figures are planning assumptions set from the market research in business/research (October 2026) and should be replaced by the owner's own numbers.
A5: Service lines (year 1 run rate; months 1 to 6 ramp up via the seasonal factors)
A6: Service line | B6: Jobs per month at run rate | C6: Average ticket ($) | D6: Materials, equipment and subs (% of price) | E6: Revenue per month at run rate ($) | F6: Source / note
A7: Service calls and repairs | B7: 14 | C7: 350 | D7: 0.2 | E7: =B7*C7 | F7: First-hour $175 to $250 then hourly; MA service fees $75 to $175 (HomeGuide Lowell)
A8: Panel upgrades and service changes | B8: 2 | C8: 4200 | D8: 0.35 | E8: =B8*C8 | F8: JS price $3,000 to $6,000; MA market $2,500 to $8,000, avg about $4,000 (EngineerFix)
A9: EV charger installations | B9: 2.5 | C9: 1600 | D9: 0.3 | E9: =B9*C9 | F9: JS $900 to $2,500 wiring; MA installed $1,200 to $3,000 (NuWatt); charger supplied on some jobs
A10: Standby generators | B10: 0.4 | C10: 14000 | D10: 0.58 | E10: =B10*C10 | F10: 20 to 26 kW with transfer switch; Boston area $12,000 to $22,000 (ConsumerAffairs); unit and ATS are most of the cost
A11: Generator inlets and interlocks | B11: 0.8 | C11: 1300 | D11: 0.35 | E11: =B11*C11 | F11: JS $900 to $1,800
A12: Lighting and fans | B12: 3 | C12: 1100 | D12: 0.35 | E12: =B12*C12 | F12: Six-light kitchen $1,200 to $2,000; fan $200 to $450
A13: Remodel contracting | B13: 0.12 | C13: 35000 | D13: 0.6 | E13: =B13*C13 | F13: Basement, kitchen or bath at fixed price; subs and materials about 60%
A14: Total at run rate | B14: =SUM(B7:B13) | D14: =IF(E14=0,0,SUMPRODUCT(D7:D13,E7:E13)/E14) | E14: =SUM(E7:E13) | F14: Blended material cost share
A16: Growth and pricing
A17: Price increase, year 2 (applies to all tickets) | B17: 0.03
A18: Price increase, year 3 | B18: 0.03
A19: Volume growth of the base lines, year 2 (owner + apprentice efficiency, referrals) | B19: 0.12
A20: Volume growth of the base lines, year 3 | B20: 0.06
A21: Revenue added per journeyman at full productivity ($ per month) | B21: 17000
A22: Material and sub cost on journeyman revenue (% of price) | B22: 0.35
A23: Journeyman ramp: month 1 of hire at 50%, month 2 at 75%, full from month 3
A25: Seasonality (multiplies run-rate revenue; year 1 row includes the start-up ramp)
A26: Month of year | B26: Average | C26: 1 | D26: 2 | E26: 3 | F26: 4 | G26: 5 | H26: 6 | I26: 7 | J26: 8 | K26: 9 | L26: 10 | M26: 11 | N26: 12
A27: Year 1 factor (ramp plus seasons) | B27: =AVERAGE(C27:N27) | C27: 0.45 | D27: 0.55 | E27: 0.65 | F27: 0.8 | G27: 0.9 | H27: 1 | I27: 1.1 | J27: 1.1 | K27: 1 | L27: 1.1 | M27: 1 | N27: 0.85
A28: Years 2 and 3 factor (seasons only, averages 1.0) | B28: =AVERAGE(C28:N28) | C28: 0.75 | D28: 0.8 | E28: 0.9 | F28: 1 | G28: 1.1 | H28: 1.15 | I28: 1.15 | J28: 1.1 | K28: 1.05 | L28: 1.1 | M28: 1 | N28: 0.9
A29: Winter trough January and February, peak June to August, rebate-deadline push in October (TCNECA, ServiceTitan seasonality data).
A31: Staffing
A32: Role | B32: Hourly wage ($) | C32: Start month | D32: Hours per month | E32: Burden (payroll tax, workers comp, PTO) | F32: Annual raise
A33: Apprentice (registered, works 1:1 with a licensed electrician) | B33: 24 | C33: 2 | D33: 173.33 | E33: 0.15 | F33: 0.03
A34: Journeyman electrician 1 | B34: 40 | C34: 16 | D34: 173.33 | E34: 0.15 | F34: 0.03
A35: Journeyman electrician 2 (second van) | B35: 40 | C35: 28 | D35: 173.33 | E35: 0.15 | F35: 0.03
A36: Boston journeyman median $38.59 per hour (PayScale 2026); MA electrician median wage about $80k (BLS OEWS). Burden: FICA 7.65% + MA workers comp class 5190 about 1.5% + PTO and training.
A37: Owner draw per month, months 1 to 3 ($) | B37: 4000
A38: Owner draw per month, months 4 to 6 ($) | B38: 6000
A39: Owner draw per month, months 7 to 12 ($) | B39: 7000
A40: Owner draw per month, year 2 ($) | B40: 7500
A41: Owner draw per month, year 3 ($) | B41: 8333
A42: Office help from month 4 ($ per month, about 10 hours a week) | B42: 500 | C42: 4
A44: Overhead ($ per month unless noted)
A45: Field-service software (Jobber Connect or Housecall Pro Essentials) | B45: 150
A46: Accounting software (QuickBooks Online Essentials) | B46: 80
A47: Google Workspace and business phone (VoIP) | B47: 60
A48: Cell and data, two lines | B48: 110
A49: Bookkeeper | B49: 400
A50: CPA (annual $1,500 spread monthly) | B50: 125
A51: Licenses, continuing education, chamber dues | B51: 60
A52: Tool replacement and small equipment | B52: 200
A53: Uniforms and PPE | B53: 60
A54: Office supplies and misc | B54: 100
A55: Storage unit or yard space | B55: 150
A56: Fixed overhead per month, before vehicles and insurance | B56: =SUM(B45:B55)
A57: Overhead inflation per year | B57: 0.03
A59: Vehicles
A60: Van 1 purchase price ($, used 2021 to 2023 Transit or ProMaster) | B60: 36000
A61: Van 1 down payment ($) | B61: 6000
A62: Van loan interest rate (annual) | B62: 0.09
A63: Van loan term (months) | B63: 60
A64: Van loan payment ($ per month) | B64: =-PMT(B62/12,B63,B60-B61)
A65: Depreciation per van ($ per month, 5-year straight line) | B65: =B60/60
A66: Fuel per van ($ per month) | B66: 450
A67: Maintenance and tires per van ($ per month) | B67: 150
A68: Van 2 purchased in month (same price and terms as van 1) | B68: 28
A69: Used-van pricing from CarGurus and TrueCar averages; financing 5 to 15% APR market (Crestmont Capital).
A71: Insurance ($ per year)
A72: General liability, $1M per occurrence / $2M aggregate | B72: 900
A73: Commercial auto, per van | B73: 2000
A74: Workers compensation rate, MA class 5190 (per $1 of payroll) | B74: 0.01475
A75: Tools and equipment (inland marine) | B75: 400
A76: Umbrella, $1M | B76: 1000
A77: Fixed insurance per month, one van | B77: =(B72+B73+B75+B76)/12
A78: Insureon medians for electricians: GL $684, auto $1,682, tools $169 to $494 per year. Workers comp is computed from payroll in the Monthly sheet.
A80: Marketing
A81: Year 1 spend by month ($) | B81: =SUM(C81:N81) | C81: 6000 | D81: 3200 | E81: 2600 | F81: 2300 | G81: 2300 | H81: 2300 | I81: 2100 | J81: 2100 | K81: 2000 | L81: 2000 | M81: 1900 | N81: 1700
A82: Year 2 marketing (% of revenue) | B82: 0.08
A83: Year 3 marketing (% of revenue) | B83: 0.07
A84: Month 1 includes the van wrap, citations and launch; Local Services Ads $1,000 to $1,500 a month from month 2 or 3. Home-services benchmark 5 to 12% of revenue.
A86: Collections and fees
A87: Card and bank fees (% of revenue) | B87: 0.015
A88: Revenue collected in the month of the job (%) | B88: 0.9
A89: Revenue collected the following month (%) | B89: =1-B88
A90: Materials paid in the month of the job (%; supply houses on net-30 shift the rest) | B90: 1
A91: Line of credit available ($, undrawn) | B91: 25000
A92: Residential service and installs are paid at completion by card or bank transfer; deposits on installs are capped at one-third under MA home-improvement law.

Sheet Startup Costs
A1: Startup costs and sources of funds
A2: Low and high are researched 2025 to 2026 price ranges; Plan is the budget used in the model. Edit the Plan column.
A4: Item | B4: Low ($) | C4: High ($) | D4: Plan ($) | E4: Basis
A5: Work van, used 2021 to 2023 (financed; see Vehicles) | B5: 34000 | C5: 43000 | D5: =Assumptions!$B$60 | E5: CarGurus and TrueCar used-van averages; financed with the down payment below
A6: Van upfit: shelving, partition, ladder rack | B6: 2500 | C6: 6500 | D6: 4000 | E6: Ranger Design and Adrian Steel packages; DIY builds about $2,500
A7: Vehicle wrap or lettering | B7: 1200 | C7: 7500 | D7: 3000 | E7: Partial wrap $1,200 to $3,500; full wrap to $7,500
A8: Hand and power tools (top-up; owner keeps his own) | B8: 1000 | C8: 12000 | D8: 4500 | E8: Jobber tool list $1,000 to $2,800; pro kits to $12,000
A9: Test equipment: multimeter, clamp meter, insulation tester | B9: 1500 | C9: 4000 | D9: 2500 | E9: Fluke 87V about $500; Fluke 1587 about $1,250; clamp $600 to $1,150
A10: Ladders, bender, fish tapes | B10: 520 | C10: 1320 | D10: 900 | E10: 28-ft fiberglass $420 to $920; bender and tapes $100 to $400
A11: Initial parts and wire inventory | B11: 4000 | C11: 7000 | D11: 5000 | E11: Stocked service van carries $5,000 to $7,000
A12: Tablet, laptop and phone | B12: 600 | C12: 3500 | D12: 1800 | E12: iPad plus case, or a rugged tablet
A13: Software setup and first two months | B13: 300 | C13: 1200 | D13: 600 | E13: Jobber or Housecall Pro, QuickBooks, Workspace, VoIP
A14: Uniforms and PPE | B14: 300 | C14: 800 | D14: 600 | E14: Embroidered shirts about $26.50 each
A15: Domain, hosting, listings (website already built) | B15: 200 | C15: 1500 | D15: 600 | E15: Netlify free tier; domain; citation listings
A16: Licenses and registrations: LLC, HIC and Guaranty Fund, CSL, DBA | B16: 900 | C16: 1300 | D16: 1100 | E16: LLC $500; HIC $150 + $100 fund; CSL $150 + exam; DBA $25 to $65
A17: Insurance down payments (about 25% of the annual program) | B17: 1000 | C17: 2500 | D17: 1400 | E17: GL, auto, workers comp, tools, umbrella about $5,500 a year
... A21: Working capital reserve (covers the slow first months) | B21: 15000 | C21: 40000 | D21: 30000 | E21: About three months of overhead plus owner draw at the reduced early rate
A22: Total startup uses | B22: =SUM(B5:B21) | C22: =SUM(C5:C21) | D22: =SUM(D5:D21)
A24: Sources of funds | D24: Plan ($)
A25: Van loan (purchase price less down payment) | D25: =Assumptions!$B$60-Assumptions!$B$61
A26: Owner cash injection from the S&T Electrical sale proceeds | D26: =D22-D25
A27: Line of credit, arranged but undrawn (seasonal buffer) | D27: =Assumptions!$B$91
A28: Total sources used at launch | D28: =D25+D26
A29: Owner injection as a share of uses (lenders look for 10 to 20% minimum) | D29: =IF(D22=0,0,D26/D22)

Sheet Annual Summary
A1: Three-year summary
A2: Sums of the Monthly sheet by year. Net profit is after a market-rate owner salary (the owner draw).
B4: Year 1 | C4: Year 2 | D4: Year 3 | E4: Note
A5: Revenue | B5: =SUMIFS(Monthly!$C$20:$AL$20,Monthly!$C$3:$AL$3,1) | C5: =SUMIFS(Monthly!$C$20:$AL$20,Monthly!$C$3:$AL$3,2) | D5: =SUMIFS(Monthly!$C$20:$AL$20,Monthly!$C$3:$AL$3,3)
A6: Materials, equipment and subcontractors | B6: =SUMIFS(Monthly!$C$32:$AL$32,Monthly!$C$3:$AL$3,1) | C6: =SUMIFS(Monthly!$C$32:$AL$32,Monthly!$C$3:$AL$3,2) | D6: =SUMIFS(Monthly!$C$32:$AL$32,Monthly!$C$3:$AL$3,3)
A7: Gross profit after materials | B7: =SUMIFS(Monthly!$C$33:$AL$33,Monthly!$C$3:$AL$3,1) | C7: =SUMIFS(Monthly!$C$33:$AL$33,Monthly!$C$3:$AL$3,2) | D7: =SUMIFS(Monthly!$C$33:$AL$33,Monthly!$C$3:$AL$3,3)
A8: Gross margin after materials | B8: =IF(B5=0,0,B7/B5) | C8: =IF(C5=0,0,C7/C5) | D8: =IF(D5=0,0,D7/D5) | E8: Benchmark 55%+ on residential service, 30 to 50% service-focused shops (Simpro, Lightning Path)
A9: Field labor | B9: =SUMIFS(Monthly!$C$40:$AL$40,Monthly!$C$3:$AL$3,1) | C9: =SUMIFS(Monthly!$C$40:$AL$40,Monthly!$C$3:$AL$3,2) | D9: =SUMIFS(Monthly!$C$40:$AL$40,Monthly!$C$3:$AL$3,3)
A10: Gross profit after labor | B10: =SUMIFS(Monthly!$C$41:$AL$41,Monthly!$C$3:$AL$3,1) | C10: =SUMIFS(Monthly!$C$41:$AL$41,Monthly!$C$3:$AL$3,2) | D10: =SUMIFS(Monthly!$C$41:$AL$41,Monthly!$C$3:$AL$3,3)
A11: Operating expenses (incl. marketing, depreciation, interest) | B11: =SUMIFS(Monthly!$C$54:$AL$54,Monthly!$C$3:$AL$3,1) | C11: =SUMIFS(Monthly!$C$54:$AL$54,Monthly!$C$3:$AL$3,2) | D11: =SUMIFS(Monthly!$C$54:$AL$54,Monthly!$C$3:$AL$3,3)
A12: of which marketing | B12: =SUMIFS(Monthly!$C$50:$AL$50,Monthly!$C$3:$AL$3,1) | C12: =SUMIFS(Monthly!$C$50:$AL$50,Monthly!$C$3:$AL$3,2) | D12: =SUMIFS(Monthly!$C$50:$AL$50,Monthly!$C$3:$AL$3,3) | E12: Year 1 about 9 to 11% of revenue, then 8% and 7%
A13: Operating profit before owner compensation | B13: =SUMIFS(Monthly!$C$55:$AL$55,Monthly!$C$3:$AL$3,1) | C13: =SUMIFS(Monthly!$C$55:$AL$55,Monthly!$C$3:$AL$3,2) | D13: =SUMIFS(Monthly!$C$55:$AL$55,Monthly!$C$3:$AL$3,3)
A14: Owner draw (salary) | B14: =SUMIFS(Monthly!$C$56:$AL$56,Monthly!$C$3:$AL$3,1) | C14: =SUMIFS(Monthly!$C$56:$AL$56,Monthly!$C$3:$AL$3,2) | D14: =SUMIFS(Monthly!$C$56:$AL$56,Monthly!$C$3:$AL$3,3)
A15: Net profit before tax | B15: =SUMIFS(Monthly!$C$57:$AL$57,Monthly!$C$3:$AL$3,1) | C15: =SUMIFS(Monthly!$C$57:$AL$57,Monthly!$C$3:$AL$3,2) | D15: =SUMIFS(Monthly!$C$57:$AL$57,Monthly!$C$3:$AL$3,3) | E15: After the owner's salary. Industry median net 5 to 6%, top quartile 10 to 12% (NECA via Simpro)
A16: Net margin | B16: =IF(B5=0,0,B15/B5) | C16: =IF(C5=0,0,C15/C5) | D16: =IF(D5=0,0,D15/D5)
A17: Owner's total take (draw plus net profit) | B17: =B14+B15 | C17: =C14+C15 | D17: =D14+D15
A19: Operations
A20: Jobs completed (base lines) | B20: =SUMIFS(Monthly!$C$21:$AL$21,Monthly!$C$3:$AL$3,1) | C20: =SUMIFS(Monthly!$C$21:$AL$21,Monthly!$C$3:$AL$3,2) | D20: =SUMIFS(Monthly!$C$21:$AL$21,Monthly!$C$3:$AL$3,3)
A21: Average revenue per base job | B21: =IF(B20=0,0,(B5-B24)/B20) | C21: =IF(C20=0,0,(C5-C24)/C20) | D21: =IF(D20=0,0,(D5-D24)/D20)
A22: Vans in service at year end | B22: =INDEX(Monthly!$C$46:$AL$46,1,12) | C22: =INDEX(Monthly!$C$46:$AL$46,1,24) | D22: =INDEX(Monthly!$C$46:$AL$46,1,36)
A23: Field people incl. owner at year end | B23: =1+IF(12*1>=Assumptions!$C$33,1,0)+IF(12*1>=Assumptions!$C$34,1,0)+IF(12*1>=Assumptions!$C$35,1,0) | C23: =1+IF(12*2>=Assumptions!$C$33,1,0)+IF(12*2>=Assumptions!$C$34,1,0)+IF(12*2>=Assumptions!$C$35,1,0) | D23: =1+IF(12*3>=Assumptions!$C$33,1,0)+IF(12*3>=Assumptions!$C$34,1,0)+IF(12*3>=Assumptions!$C$35,1,0)
A24: Revenue added by journeymen | B24: =SUMIFS(Monthly!$C$18:$AL$18,Monthly!$C$3:$AL$3,1)+SUMIFS(Monthly!$C$19:$AL$19,Monthly!$C$3:$AL$3,1) | C24: =SUMIFS(Monthly!$C$18:$AL$18,Monthly!$C$3:$AL$3,2)+SUMIFS(Monthly!$C$19:$AL$19,Monthly!$C$3:$AL$3,2) | D24: =SUMIFS(Monthly!$C$18:$AL$18,Monthly!$C$3:$AL$3,3)+SUMIFS(Monthly!$C$19:$AL$19,Monthly!$C$3:$AL$3,3)
A25: Revenue per field person | B25: =IF(B23=0,0,B5/B23) | C25: =IF(C23=0,0,C5/C23) | D25: =IF(D23=0,0,D5/D23) | E25: Benchmark $207k to $400k per technician; the owner spends about half his time off the tools
A27: Cash and debt
A28: Lowest month-end cash in the year | B28: =MIN(INDEX(Monthly!$C$70:$AL$70,1,1):INDEX(Monthly!$C$70:$AL$70,1,12)) | C28: =MIN(INDEX(Monthly!$C$70:$AL$70,1,13):INDEX(Monthly!$C$70:$AL$70,1,24)) | D28: =MIN(INDEX(Monthly!$C$70:$AL$70,1,25):INDEX(Monthly!$C$70:$AL$70,1,36)) | E28: Must stay above zero without drawing the line of credit
A29: Cash at year end | B29: =INDEX(Monthly!$C$70:$AL$70,1,12) | C29: =INDEX(Monthly!$C$70:$AL$70,1,24) | D29: =INDEX(Monthly!$C$70:$AL$70,1,36)
A30: Annual debt service (van loans) | B30: =SUMIFS(Monthly!$C$65:$AL$65,Monthly!$C$3:$AL$3,1) | C30: =SUMIFS(Monthly!$C$65:$AL$65,Monthly!$C$3:$AL$3,2) | D30: =SUMIFS(Monthly!$C$65:$AL$65,Monthly!$C$3:$AL$3,3)
A31: Debt service coverage (net profit + interest + depreciation) / debt service | B31: =IF(B30=0,0,(B15+SUMIFS(Monthly!$C$53:$AL$53,Monthly!$C$3:$AL$3,1)+SUMIFS(Monthly!$C$52:$AL$52,Monthly!$C$3:$AL$3,1))/B30) | C31: =IF(C30=0,0,(C15+SUMIFS(Monthly!$C$53:$AL$53,Monthly!$C$3:$AL$3,2)+SUMIFS(Monthly!$C$52:$AL$52,Monthly!$C$3:$AL$3,2))/C30) | D31: =IF(D30=0,0,(D15+SUMIFS(Monthly!$C$53:$AL$53,Monthly!$C$3:$AL$3,3)+SUMIFS(Monthly!$C$52:$AL$52,Monthly!$C$3:$AL$3,3))/D30) | E31: Lenders look for 1.25x or better
A33: Break-even
A34: Fixed costs (labor, operating expenses, owner draw) | B34: =B9+B11+B14 | C34: =C9+C11+C14 | D34: =D9+D11+D14
A35: Break-even revenue at the year's gross margin | B35: =IF(B8=0,0,B34/B8) | C35: =IF(C8=0,0,C34/C8) | D35: =IF(D8=0,0,D34/D8) | E35: Revenue needed to cover all costs including the owner's salary
A36: Revenue above (below) break-even | B36: =B5-B35 | C36: =C5-C35 | D36: =D5-D35
A37: Break-even revenue per month | B37: =B35/12 | C37: =C35/12 | D37: =D35/12

Sheet Monthly
A1: Monthly projection, months 1 to 36 (P&L and cash flow)
A2: All cells are formulas driven by the Assumptions sheet. Month 1 is the first month of operations.
A3: Year | C3: =IF(C4<=12,1,IF(C4<=24,2,3)) | D3: =IF(D4<=12,1,IF(D4<=24,2,3)) | E3: =IF(E4<=12,1,IF(E4<=24,2,3)) | F3: =IF(F4<=12,1,IF(F4<=24,2,3)) | G3: =IF(G4<=12,1,IF(G4<=24,2,3)) | H3: =IF(H4<=12,1,IF(H4<=24,2,3)) | I3: =IF(I4<=12,1,IF(I4<=24,2,3)) | J3: =IF(J4<=12,1,IF(J4<=24,2,3)) | ... AL3: =IF(AL4<=12,1,IF(AL4<=24,2,3))
A4: Month | C4: 1 | D4: 2 | E4: 3 | F4: 4 | G4: 5 | H4: 6 | I4: 7 | J4: 8 | K4: 9 | L4: 10 | M4: 11 | N4: 12 | O4: 13 | P4: 14 | Q4: 15 | R4: 16 | S4: 17 | T4: 18 | U4: 19 | V4: 20 | W4: 21 | X4: 22 | Y4: 23 | Z4: 24 | AA4: 25 | AB4: 26 | AC4: 27 | AD4: 28 | AE4: 29 | AF4: 30 | AG4: 31 | AH4: 32 | AI4: 33 | AJ4: 34 | AK4: 35 | AL4: 36
A5: Factors
A6: Seasonal factor | B6: x | C6: =IF(C$3=1,INDEX(Assumptions!$C$27:$N$27,1,MOD(C$4-1,12)+1),INDEX(Assumptions!$C$28:$N$28,1,MOD(C$4-1,12)+1)) | D6: =IF(D$3=1,INDEX(Assumptions!$C$27:$N$27,1,MOD(D$4-1,12)+1),INDEX(Assumptions!$C$28:$N$28,1,MOD(D$4-1,12)+1)) | E6: =IF(E$3=1,INDEX(Assumptions!$C$27:$N$27,1,MOD(E$4-1,12)+1),INDEX(Assumptions!$C$28:$N$28,1,MOD(E$4-1,12)+1)) | F6: =IF(F$3=1,INDEX(Assumptions!$C$27:$N$27,1,MOD(F$4-1,12)+1),INDEX(Assumptions!$C$28:$N$28,1,MOD(F$4-1,12)+1)) | G6: =IF(G$3=1,INDEX(Assumptions!$C$27:$N$27,1,MOD(G$4-1,12)+1),INDEX(Assumptions!$C$28:$N$28,1,MOD(G$4-1,12)+1)) | H6: =IF(H$3=1,INDEX(Assumptions!$C$27:$N$27,1,MOD(H$4-1,12)+1),INDEX(Assumptions!$C$28:$N$28,1,MOD(H$4-1,12)+1)) | I6: =IF(I$3=1,INDEX(Assumptions!$C$27:$N$27,1,MOD(I$4-1,12)+1),INDEX(Assumptions!$C$28:$N$28,1,MOD(I$4-1,12)+1)) | J6: =IF(J$3=1,INDEX(Assumptions!$C$27:$N$27,1,MOD(J$4-1,12)+1),INDEX(Assumptions!$C$28:$N$28,1,MOD(J$4-1,12)+1)) | ... AL6: =IF(AL$3=1,INDEX(Assumptions!$C$27:$N$27,1,MOD(AL$4-1,12)+1),INDEX(Assumptions!$C$28:$N$28,1,MOD(AL$4-1,12)+1))
A7: Base volume factor | B7: x | C7: =IF(C$3=1,1,IF(C$3=2,1+Assumptions!$B$19,(1+Assumptions!$B$19)*(1+Assumptions!$B$20))) | D7: =IF(D$3=1,1,IF(D$3=2,1+Assumptions!$B$19,(1+Assumptions!$B$19)*(1+Assumptions!$B$20))) | E7: =IF(E$3=1,1,IF(E$3=2,1+Assumptions!$B$19,(1+Assumptions!$B$19)*(1+Assumptions!$B$20))) | F7: =IF(F$3=1,1,IF(F$3=2,1+Assumptions!$B$19,(1+Assumptions!$B$19)*(1+Assumptions!$B$20))) | G7: =IF(G$3=1,1,IF(G$3=2,1+Assumptions!$B$19,(1+Assumptions!$B$19)*(1+Assumptions!$B$20))) | H7: =IF(H$3=1,1,IF(H$3=2,1+Assumptions!$B$19,(1+Assumptions!$B$19)*(1+Assumptions!$B$20))) | I7: =IF(I$3=1,1,IF(I$3=2,1+Assumptions!$B$19,(1+Assumptions!$B$19)*(1+Assumptions!$B$20))) | J7: =IF(J$3=1,1,IF(J$3=2,1+Assumptions!$B$19,(1+Assumptions!$B$19)*(1+Assumptions!$B$20))) | ... AL7: =IF(AL$3=1,1,IF(AL$3=2,1+Assumptions!$B$19,(1+Assumptions!$B$19)*(1+Assumptions!$B$20)))
A8: Price factor | B8: x | C8: =IF(C$3=1,1,IF(C$3=2,1+Assumptions!$B$17,(1+Assumptions!$B$17)*(1+Assumptions!$B$18))) | D8: =IF(D$3=1,1,IF(D$3=2,1+Assumptions!$B$17,(1+Assumptions!$B$17)*(1+Assumptions!$B$18))) | E8: =IF(E$3=1,1,IF(E$3=2,1+Assumptions!$B$17,(1+Assumptions!$B$17)*(1+Assumptions!$B$18))) | F8: =IF(F$3=1,1,IF(F$3=2,1+Assumptions!$B$17,(1+Assumptions!$B$17)*(1+Assumptions!$B$18))) | G8: =IF(G$3=1,1,IF(G$3=2,1+Assumptions!$B$17,(1+Assumptions!$B$17)*(1+Assumptions!$B$18))) | H8: =IF(H$3=1,1,IF(H$3=2,1+Assumptions!$B$17,(1+Assumptions!$B$17)*(1+Assumptions!$B$18))) | I8: =IF(I$3=1,1,IF(I$3=2,1+Assumptions!$B$17,(1+Assumptions!$B$17)*(1+Assumptions!$B$18))) | J8: =IF(J$3=1,1,IF(J$3=2,1+Assumptions!$B$17,(1+Assumptions!$B$17)*(1+Assumptions!$B$18))) | ... AL8: =IF(AL$3=1,1,IF(AL$3=2,1+Assumptions!$B$17,(1+Assumptions!$B$17)*(1+Assumptions!$B$18)))
A10: Revenue
A11: Service calls and repairs | B11: $ | C11: =Assumptions!$B$7*Assumptions!$C$7*C$6*C$7*C$8 | D11: =Assumptions!$B$7*Assumptions!$C$7*D$6*D$7*D$8 | E11: =Assumptions!$B$7*Assumptions!$C$7*E$6*E$7*E$8 | F11: =Assumptions!$B$7*Assumptions!$C$7*F$6*F$7*F$8 | G11: =Assumptions!$B$7*Assumptions!$C$7*G$6*G$7*G$8 | H11: =Assumptions!$B$7*Assumptions!$C$7*H$6*H$7*H$8 | I11: =Assumptions!$B$7*Assumptions!$C$7*I$6*I$7*I$8 | J11: =Assumptions!$B$7*Assumptions!$C$7*J$6*J$7*J$8 | ... AL11: =Assumptions!$B$7*Assumptions!$C$7*AL$6*AL$7*AL$8
A12: Panel upgrades and service changes | B12: $ | C12: =Assumptions!$B$8*Assumptions!$C$8*C$6*C$7*C$8 | D12: =Assumptions!$B$8*Assumptions!$C$8*D$6*D$7*D$8 | E12: =Assumptions!$B$8*Assumptions!$C$8*E$6*E$7*E$8 | F12: =Assumptions!$B$8*Assumptions!$C$8*F$6*F$7*F$8 | G12: =Assumptions!$B$8*Assumptions!$C$8*G$6*G$7*G$8 | H12: =Assumptions!$B$8*Assumptions!$C$8*H$6*H$7*H$8 | I12: =Assumptions!$B$8*Assumptions!$C$8*I$6*I$7*I$8 | J12: =Assumptions!$B$8*Assumptions!$C$8*J$6*J$7*J$8 | ... AL12: =Assumptions!$B$8*Assumptions!$C$8*AL$6*AL$7*AL$8
A13: EV charger installations | B13: $ | C13: =Assumptions!$B$9*Assumptions!$C$9*C$6*C$7*C$8 | D13: =Assumptions!$B$9*Assumptions!$C$9*D$6*D$7*D$8 | E13: =Assumptions!$B$9*Assumptions!$C$9*E$6*E$7*E$8 | F13: =Assumptions!$B$9*Assumptions!$C$9*F$6*F$7*F$8 | G13: =Assumptions!$B$9*Assumptions!$C$9*G$6*G$7*G$8 | H13: =Assumptions!$B$9*Assumptions!$C$9*H$6*H$7*H$8 | I13: =Assumptions!$B$9*Assumptions!$C$9*I$6*I$7*I$8 | J13: =Assumptions!$B$9*Assumptions!$C$9*J$6*J$7*J$8 | ... AL13: =Assumptions!$B$9*Assumptions!$C$9*AL$6*AL$7*AL$8
A14: Standby generators | B14: $ | C14: =Assumptions!$B$10*Assumptions!$C$10*C$6*C$7*C$8 | D14: =Assumptions!$B$10*Assumptions!$C$10*D$6*D$7*D$8 | E14: =Assumptions!$B$10*Assumptions!$C$10*E$6*E$7*E$8 | F14: =Assumptions!$B$10*Assumptions!$C$10*F$6*F$7*F$8 | G14: =Assumptions!$B$10*Assumptions!$C$10*G$6*G$7*G$8 | H14: =Assumptions!$B$10*Assumptions!$C$10*H$6*H$7*H$8 | I14: =Assumptions!$B$10*Assumptions!$C$10*I$6*I$7*I$8 | J14: =Assumptions!$B$10*Assumptions!$C$10*J$6*J$7*J$8 | ... AL14: =Assumptions!$B$10*Assumptions!$C$10*AL$6*AL$7*AL$8
A15: Generator inlets and interlocks | B15: $ | C15: =Assumptions!$B$11*Assumptions!$C$11*C$6*C$7*C$8 | D15: =Assumptions!$B$11*Assumptions!$C$11*D$6*D$7*D$8 | E15: =Assumptions!$B$11*Assumptions!$C$11*E$6*E$7*E$8 | F15: =Assumptions!$B$11*Assumptions!$C$11*F$6*F$7*F$8 | G15: =Assumptions!$B$11*Assumptions!$C$11*G$6*G$7*G$8 | H15: =Assumptions!$B$11*Assumptions!$C$11*H$6*H$7*H$8 | I15: =Assumptions!$B$11*Assumptions!$C$11*I$6*I$7*I$8 | J15: =Assumptions!$B$11*Assumptions!$C$11*J$6*J$7*J$8 | ... AL15: =Assumptions!$B$11*Assumptions!$C$11*AL$6*AL$7*AL$8
A16: Lighting and fans | B16: $ | C16: =Assumptions!$B$12*Assumptions!$C$12*C$6*C$7*C$8 | D16: =Assumptions!$B$12*Assumptions!$C$12*D$6*D$7*D$8 | E16: =Assumptions!$B$12*Assumptions!$C$12*E$6*E$7*E$8 | F16: =Assumptions!$B$12*Assumptions!$C$12*F$6*F$7*F$8 | G16: =Assumptions!$B$12*Assumptions!$C$12*G$6*G$7*G$8 | H16: =Assumptions!$B$12*Assumptions!$C$12*H$6*H$7*H$8 | I16: =Assumptions!$B$12*Assumptions!$C$12*I$6*I$7*I$8 | J16: =Assumptions!$B$12*Assumptions!$C$12*J$6*J$7*J$8 | ... AL16: =Assumptions!$B$12*Assumptions!$C$12*AL$6*AL$7*AL$8
A17: Remodel contracting | B17: $ | C17: =Assumptions!$B$13*Assumptions!$C$13*C$6*C$7*C$8 | D17: =Assumptions!$B$13*Assumptions!$C$13*D$6*D$7*D$8 | E17: =Assumptions!$B$13*Assumptions!$C$13*E$6*E$7*E$8 | F17: =Assumptions!$B$13*Assumptions!$C$13*F$6*F$7*F$8 | G17: =Assumptions!$B$13*Assumptions!$C$13*G$6*G$7*G$8 | H17: =Assumptions!$B$13*Assumptions!$C$13*H$6*H$7*H$8 | I17: =Assumptions!$B$13*Assumptions!$C$13*I$6*I$7*I$8 | J17: =Assumptions!$B$13*Assumptions!$C$13*J$6*J$7*J$8 | ... AL17: =Assumptions!$B$13*Assumptions!$C$13*AL$6*AL$7*AL$8
A18: Journeyman 1 added revenue | B18: $ | C18: =IF(C$4<Assumptions!$C$34,0,Assumptions!$B$21*MIN(1,0.5+0.25*(C$4-Assumptions!$C$34))*C$6*C$8) | D18: =IF(D$4<Assumptions!$C$34,0,Assumptions!$B$21*MIN(1,0.5+0.25*(D$4-Assumptions!$C$34))*D$6*D$8) | E18: =IF(E$4<Assumptions!$C$34,0,Assumptions!$B$21*MIN(1,0.5+0.25*(E$4-Assumptions!$C$34))*E$6*E$8) | F18: =IF(F$4<Assumptions!$C$34,0,Assumptions!$B$21*MIN(1,0.5+0.25*(F$4-Assumptions!$C$34))*F$6*F$8) | G18: =IF(G$4<Assumptions!$C$34,0,Assumptions!$B$21*MIN(1,0.5+0.25*(G$4-Assumptions!$C$34))*G$6*G$8) | H18: =IF(H$4<Assumptions!$C$34,0,Assumptions!$B$21*MIN(1,0.5+0.25*(H$4-Assumptions!$C$34))*H$6*H$8) | I18: =IF(I$4<Assumptions!$C$34,0,Assumptions!$B$21*MIN(1,0.5+0.25*(I$4-Assumptions!$C$34))*I$6*I$8) | J18: =IF(J$4<Assumptions!$C$34,0,Assumptions!$B$21*MIN(1,0.5+0.25*(J$4-Assumptions!$C$34))*J$6*J$8) | ... AL18: =IF(AL$4<Assumptions!$C$34,0,Assumptions!$B$21*MIN(1,0.5+0.25*(AL$4-Assumptions!$C$34))*AL$6*AL$8)
A19: Journeyman 2 added revenue | B19: $ | C19: =IF(C$4<Assumptions!$C$35,0,Assumptions!$B$21*MIN(1,0.5+0.25*(C$4-Assumptions!$C$35))*C$6*C$8) | D19: =IF(D$4<Assumptions!$C$35,0,Assumptions!$B$21*MIN(1,0.5+0.25*(D$4-Assumptions!$C$35))*D$6*D$8) | E19: =IF(E$4<Assumptions!$C$35,0,Assumptions!$B$21*MIN(1,0.5+0.25*(E$4-Assumptions!$C$35))*E$6*E$8) | F19: =IF(F$4<Assumptions!$C$35,0,Assumptions!$B$21*MIN(1,0.5+0.25*(F$4-Assumptions!$C$35))*F$6*F$8) | G19: =IF(G$4<Assumptions!$C$35,0,Assumptions!$B$21*MIN(1,0.5+0.25*(G$4-Assumptions!$C$35))*G$6*G$8) | H19: =IF(H$4<Assumptions!$C$35,0,Assumptions!$B$21*MIN(1,0.5+0.25*(H$4-Assumptions!$C$35))*H$6*H$8) | I19: =IF(I$4<Assumptions!$C$35,0,Assumptions!$B$21*MIN(1,0.5+0.25*(I$4-Assumptions!$C$35))*I$6*I$8) | J19: =IF(J$4<Assumptions!$C$35,0,Assumptions!$B$21*MIN(1,0.5+0.25*(J$4-Assumptions!$C$35))*J$6*J$8) | ... AL19: =IF(AL$4<Assumptions!$C$35,0,Assumptions!$B$21*MIN(1,0.5+0.25*(AL$4-Assumptions!$C$35))*AL$6*AL$8)
A20: Total revenue | B20: $ | C20: =SUM(C11:C19) | D20: =SUM(D11:D19) | E20: =SUM(E11:E19) | F20: =SUM(F11:F19) | G20: =SUM(G11:G19) | H20: =SUM(H11:H19) | I20: =SUM(I11:I19) | J20: =SUM(J11:J19) | ... AL20: =SUM(AL11:AL19)
A21: Jobs completed (base lines) | B21: # | C21: =Assumptions!$B$7*C$6*C$7+Assumptions!$B$8*C$6*C$7+Assumptions!$B$9*C$6*C$7+Assumptions!$B$10*C$6*C$7+Assumptions!$B$11*C$6*C$7+Assumptions!$B$12*C$6*C$7+Assumptions!$B$13*C$6*C$7 | D21: =Assumptions!$B$7*D$6*D$7+Assumptions!$B$8*D$6*D$7+Assumptions!$B$9*D$6*D$7+Assumptions!$B$10*D$6*D$7+Assumptions!$B$11*D$6*D$7+Assumptions!$B$12*D$6*D$7+Assumptions!$B$13*D$6*D$7 | E21: =Assumptions!$B$7*E$6*E$7+Assumptions!$B$8*E$6*E$7+Assumptions!$B$9*E$6*E$7+Assumptions!$B$10*E$6*E$7+Assumptions!$B$11*E$6*E$7+Assumptions!$B$12*E$6*E$7+Assumptions!$B$13*E$6*E$7 | F21: =Assumptions!$B$7*F$6*F$7+Assumptions!$B$8*F$6*F$7+Assumptions!$B$9*F$6*F$7+Assumptions!$B$10*F$6*F$7+Assumptions!$B$11*F$6*F$7+Assumptions!$B$12*F$6*F$7+Assumptions!$B$13*F$6*F$7 | G21: =Assumptions!$B$7*G$6*G$7+Assumptions!$B$8*G$6*G$7+Assumptions!$B$9*G$6*G$7+Assumptions!$B$10*G$6*G$7+Assumptions!$B$11*G$6*G$7+Assumptions!$B$12*G$6*G$7+Assumptions!$B$13*G$6*G$7 | H21: =Assumptions!$B$7*H$6*H$7+Assumptions!$B$8*H$6*H$7+Assumptions!$B$9*H$6*H$7+Assumptions!$B$10*H$6*H$7+Assumptions!$B$11*H$6*H$7+Assumptions!$B$12*H$6*H$7+Assumptions!$B$13*H$6*H$7 | I21: =Assumptions!$B$7*I$6*I$7+Assumptions!$B$8*I$6*I$7+Assumptions!$B$9*I$6*I$7+Assumptions!$B$10*I$6*I$7+Assumptions!$B$11*I$6*I$7+Assumptions!$B$12*I$6*I$7+Assumptions!$B$13*I$6*I$7 | J21: =Assumptions!$B$7*J$6*J$7+Assumptions!$B$8*J$6*J$7+Assumptions!$B$9*J$6*J$7+Assumptions!$B$10*J$6*J$7+Assumptions!$B$11*J$6*J$7+Assumptions!$B$12*J$6*J$7+Assumptions!$B$13*J$6*J$7 | ... AL21: =Assumptions!$B$7*AL$6*AL$7+Assumptions!$B$8*AL$6*AL$7+Assumptions!$B$9*AL$6*AL$7+Assumptions!$B$10*AL$6*AL$7+Assumptions!$B$11*AL$6*AL$7+Assumptions!$B$12*AL$6*AL$7+Assumptions!$B$13*AL$6*AL$7
A23: Materials, equipment and subcontractors
A24: Service calls and repairs | B24: $ | C24: =C11*Assumptions!$D$7 | D24: =D11*Assumptions!$D$7 | E24: =E11*Assumptions!$D$7 | F24: =F11*Assumptions!$D$7 | G24: =G11*Assumptions!$D$7 | H24: =H11*Assumptions!$D$7 | I24: =I11*Assumptions!$D$7 | J24: =J11*Assumptions!$D$7 | ... AL24: =AL11*Assumptions!$D$7
A25: Panel upgrades and service changes | B25: $ | C25: =C12*Assumptions!$D$8 | D25: =D12*Assumptions!$D$8 | E25: =E12*Assumptions!$D$8 | F25: =F12*Assumptions!$D$8 | G25: =G12*Assumptions!$D$8 | H25: =H12*Assumptions!$D$8 | I25: =I12*Assumptions!$D$8 | J25: =J12*Assumptions!$D$8 | ... AL25: =AL12*Assumptions!$D$8
A26: EV charger installations | B26: $ | C26: =C13*Assumptions!$D$9 | D26: =D13*Assumptions!$D$9 | E26: =E13*Assumptions!$D$9 | F26: =F13*Assumptions!$D$9 | G26: =G13*Assumptions!$D$9 | H26: =H13*Assumptions!$D$9 | I26: =I13*Assumptions!$D$9 | J26: =J13*Assumptions!$D$9 | ... AL26: =AL13*Assumptions!$D$9
A27: Standby generators | B27: $ | C27: =C14*Assumptions!$D$10 | D27: =D14*Assumptions!$D$10 | E27: =E14*Assumptions!$D$10 | F27: =F14*Assumptions!$D$10 | G27: =G14*Assumptions!$D$10 | H27: =H14*Assumptions!$D$10 | I27: =I14*Assumptions!$D$10 | J27: =J14*Assumptions!$D$10 | ... AL27: =AL14*Assumptions!$D$10
A28: Generator inlets and interlocks | B28: $ | C28: =C15*Assumptions!$D$11 | D28: =D15*Assumptions!$D$11 | E28: =E15*Assumptions!$D$11 | F28: =F15*Assumptions!$D$11 | G28: =G15*Assumptions!$D$11 | H28: =H15*Assumptions!$D$11 | I28: =I15*Assumptions!$D$11 | J28: =J15*Assumptions!$D$11 | ... AL28: =AL15*Assumptions!$D$11
A29: Lighting and fans | B29: $ | C29: =C16*Assumptions!$D$12 | D29: =D16*Assumptions!$D$12 | E29: =E16*Assumptions!$D$12 | F29: =F16*Assumptions!$D$12 | G29: =G16*Assumptions!$D$12 | H29: =H16*Assumptions!$D$12 | I29: =I16*Assumptions!$D$12 | J29: =J16*Assumptions!$D$12 | ... AL29: =AL16*Assumptions!$D$12
A30: Remodel contracting | B30: $ | C30: =C17*Assumptions!$D$13 | D30: =D17*Assumptions!$D$13 | E30: =E17*Assumptions!$D$13 | F30: =F17*Assumptions!$D$13 | G30: =G17*Assumptions!$D$13 | H30: =H17*Assumptions!$D$13 | I30: =I17*Assumptions!$D$13 | J30: =J17*Assumptions!$D$13 | ... AL30: =AL17*Assumptions!$D$13
A31: On journeyman revenue | B31: $ | C31: =(C18+C19)*Assumptions!$B$22 | D31: =(D18+D19)*Assumptions!$B$22 | E31: =(E18+E19)*Assumptions!$B$22 | F31: =(F18+F19)*Assumptions!$B$22 | G31: =(G18+G19)*Assumptions!$B$22 | H31: =(H18+H19)*Assumptions!$B$22 | I31: =(I18+I19)*Assumptions!$B$22 | J31: =(J18+J19)*Assumptions!$B$22 | ... AL31: =(AL18+AL19)*Assumptions!$B$22
A32: Total materials, equipment and subs | B32: $ | C32: =SUM(C24:C31) | D32: =SUM(D24:D31) | E32: =SUM(E24:E31) | F32: =SUM(F24:F31) | G32: =SUM(G24:G31) | H32: =SUM(H24:H31) | I32: =SUM(I24:I31) | J32: =SUM(J24:J31) | ... AL32: =SUM(AL24:AL31)
A33: Gross profit after materials | B33: $ | C33: =C20-C32 | D33: =D20-D32 | E33: =E20-E32 | F33: =F20-F32 | G33: =G20-G32 | H33: =H20-H32 | I33: =I20-I32 | J33: =J20-J32 | ... AL33: =AL20-AL32
A34: Gross margin after materials | B34: % | C34: =IF(C20=0,0,C33/C20) | D34: =IF(D20=0,0,D33/D20) | E34: =IF(E20=0,0,E33/E20) | F34: =IF(F20=0,0,F33/F20) | G34: =IF(G20=0,0,G33/G20) | H34: =IF(H20=0,0,H33/H20) | I34: =IF(I20=0,0,I33/I20) | J34: =IF(J20=0,0,J33/J20) | ... AL34: =IF(AL20=0,0,AL33/AL20)
A36: Field labor (wages plus burden)
A37: Apprentice | B37: $ | C37: =IF(C$4<Assumptions!$C$33,0,Assumptions!$B$33*Assumptions!$D$33*(1+Assumptions!$E$33)*(1+Assumptions!$F$33)^(C$3-1)) | D37: =IF(D$4<Assumptions!$C$33,0,Assumptions!$B$33*Assumptions!$D$33*(1+Assumptions!$E$33)*(1+Assumptions!$F$33)^(D$3-1)) | E37: =IF(E$4<Assumptions!$C$33,0,Assumptions!$B$33*Assumptions!$D$33*(1+Assumptions!$E$33)*(1+Assumptions!$F$33)^(E$3-1)) | F37: =IF(F$4<Assumptions!$C$33,0,Assumptions!$B$33*Assumptions!$D$33*(1+Assumptions!$E$33)*(1+Assumptions!$F$33)^(F$3-1)) | G37: =IF(G$4<Assumptions!$C$33,0,Assumptions!$B$33*Assumptions!$D$33*(1+Assumptions!$E$33)*(1+Assumptions!$F$33)^(G$3-1)) | H37: =IF(H$4<Assumptions!$C$33,0,Assumptions!$B$33*Assumptions!$D$33*(1+Assumptions!$E$33)*(1+Assumptions!$F$33)^(H$3-1)) | I37: =IF(I$4<Assumptions!$C$33,0,Assumptions!$B$33*Assumptions!$D$33*(1+Assumptions!$E$33)*(1+Assumptions!$F$33)^(I$3-1)) | J37: =IF(J$4<Assumptions!$C$33,0,Assumptions!$B$33*Assumptions!$D$33*(1+Assumptions!$E$33)*(1+Assumptions!$F$33)^(J$3-1)) | ... AL37: =IF(AL$4<Assumptions!$C$33,0,Assumptions!$B$33*Assumptions!$D$33*(1+Assumptions!$E$33)*(1+Assumptions!$F$33)^(AL$3-1))
A38: Journeyman 1 | B38: $ | C38: =IF(C$4<Assumptions!$C$34,0,Assumptions!$B$34*Assumptions!$D$34*(1+Assumptions!$E$34)*(1+Assumptions!$F$34)^(C$3-1)) | D38: =IF(D$4<Assumptions!$C$34,0,Assumptions!$B$34*Assumptions!$D$34*(1+Assumptions!$E$34)*(1+Assumptions!$F$34)^(D$3-1)) | E38: =IF(E$4<Assumptions!$C$34,0,Assumptions!$B$34*Assumptions!$D$34*(1+Assumptions!$E$34)*(1+Assumptions!$F$34)^(E$3-1)) | F38: =IF(F$4<Assumptions!$C$34,0,Assumptions!$B$34*Assumptions!$D$34*(1+Assumptions!$E$34)*(1+Assumptions!$F$34)^(F$3-1)) | G38: =IF(G$4<Assumptions!$C$34,0,Assumptions!$B$34*Assumptions!$D$34*(1+Assumptions!$E$34)*(1+Assumptions!$F$34)^(G$3-1)) | H38: =IF(H$4<Assumptions!$C$34,0,Assumptions!$B$34*Assumptions!$D$34*(1+Assumptions!$E$34)*(1+Assumptions!$F$34)^(H$3-1)) | I38: =IF(I$4<Assumptions!$C$34,0,Assumptions!$B$34*Assumptions!$D$34*(1+Assumptions!$E$34)*(1+Assumptions!$F$34)^(I$3-1)) | J38: =IF(J$4<Assumptions!$C$34,0,Assumptions!$B$34*Assumptions!$D$34*(1+Assumptions!$E$34)*(1+Assumptions!$F$34)^(J$3-1)) | ... AL38: =IF(AL$4<Assumptions!$C$34,0,Assumptions!$B$34*Assumptions!$D$34*(1+Assumptions!$E$34)*(1+Assumptions!$F$34)^(AL$3-1))
A39: Journeyman 2 | B39: $ | C39: =IF(C$4<Assumptions!$C$35,0,Assumptions!$B$35*Assumptions!$D$35*(1+Assumptions!$E$35)*(1+Assumptions!$F$35)^(C$3-1)) | D39: =IF(D$4<Assumptions!$C$35,0,Assumptions!$B$35*Assumptions!$D$35*(1+Assumptions!$E$35)*(1+Assumptions!$F$35)^(D$3-1)) | E39: =IF(E$4<Assumptions!$C$35,0,Assumptions!$B$35*Assumptions!$D$35*(1+Assumptions!$E$35)*(1+Assumptions!$F$35)^(E$3-1)) | F39: =IF(F$4<Assumptions!$C$35,0,Assumptions!$B$35*Assumptions!$D$35*(1+Assumptions!$E$35)*(1+Assumptions!$F$35)^(F$3-1)) | G39: =IF(G$4<Assumptions!$C$35,0,Assumptions!$B$35*Assumptions!$D$35*(1+Assumptions!$E$35)*(1+Assumptions!$F$35)^(G$3-1)) | H39: =IF(H$4<Assumptions!$C$35,0,Assumptions!$B$35*Assumptions!$D$35*(1+Assumptions!$E$35)*(1+Assumptions!$F$35)^(H$3-1)) | I39: =IF(I$4<Assumptions!$C$35,0,Assumptions!$B$35*Assumptions!$D$35*(1+Assumptions!$E$35)*(1+Assumptions!$F$35)^(I$3-1)) | J39: =IF(J$4<Assumptions!$C$35,0,Assumptions!$B$35*Assumptions!$D$35*(1+Assumptions!$E$35)*(1+Assumptions!$F$35)^(J$3-1)) | ... AL39: =IF(AL$4<Assumptions!$C$35,0,Assumptions!$B$35*Assumptions!$D$35*(1+Assumptions!$E$35)*(1+Assumptions!$F$35)^(AL$3-1))
A40: Total field labor | B40: $ | C40: =SUM(C37:C39) | D40: =SUM(D37:D39) | E40: =SUM(E37:E39) | F40: =SUM(F37:F39) | G40: =SUM(G37:G39) | H40: =SUM(H37:H39) | I40: =SUM(I37:I39) | J40: =SUM(J37:J39) | ... AL40: =SUM(AL37:AL39)
A41: Gross profit after labor | B41: $ | C41: =C33-C40 | D41: =D33-D40 | E41: =E33-E40 | F41: =F33-F40 | G41: =G33-G40 | H41: =H33-H40 | I41: =I33-I40 | J41: =J33-J40 | ... AL41: =AL33-AL40
A43: Operating expenses
A44: Fixed overhead (software, phone, bookkeeping, tools, misc) | B44: $ | C44: =Assumptions!$B$56*(1+Assumptions!$B$57)^(C$3-1) | D44: =Assumptions!$B$56*(1+Assumptions!$B$57)^(D$3-1) | E44: =Assumptions!$B$56*(1+Assumptions!$B$57)^(E$3-1) | F44: =Assumptions!$B$56*(1+Assumptions!$B$57)^(F$3-1) | G44: =Assumptions!$B$56*(1+Assumptions!$B$57)^(G$3-1) | H44: =Assumptions!$B$56*(1+Assumptions!$B$57)^(H$3-1) | I44: =Assumptions!$B$56*(1+Assumptions!$B$57)^(I$3-1) | J44: =Assumptions!$B$56*(1+Assumptions!$B$57)^(J$3-1) | ... AL44: =Assumptions!$B$56*(1+Assumptions!$B$57)^(AL$3-1)
A45: Office help | B45: $ | C45: =IF(C$4<Assumptions!$C$42,0,Assumptions!$B$42*(1+Assumptions!$B$57)^(C$3-1)) | D45: =IF(D$4<Assumptions!$C$42,0,Assumptions!$B$42*(1+Assumptions!$B$57)^(D$3-1)) | E45: =IF(E$4<Assumptions!$C$42,0,Assumptions!$B$42*(1+Assumptions!$B$57)^(E$3-1)) | F45: =IF(F$4<Assumptions!$C$42,0,Assumptions!$B$42*(1+Assumptions!$B$57)^(F$3-1)) | G45: =IF(G$4<Assumptions!$C$42,0,Assumptions!$B$42*(1+Assumptions!$B$57)^(G$3-1)) | H45: =IF(H$4<Assumptions!$C$42,0,Assumptions!$B$42*(1+Assumptions!$B$57)^(H$3-1)) | I45: =IF(I$4<Assumptions!$C$42,0,Assumptions!$B$42*(1+Assumptions!$B$57)^(I$3-1)) | J45: =IF(J$4<Assumptions!$C$42,0,Assumptions!$B$42*(1+Assumptions!$B$57)^(J$3-1)) | ... AL45: =IF(AL$4<Assumptions!$C$42,0,Assumptions!$B$42*(1+Assumptions!$B$57)^(AL$3-1))
A46: Vans in service | B46: # | C46: =1+IF(C$4>=Assumptions!$B$68,1,0) | D46: =1+IF(D$4>=Assumptions!$B$68,1,0) | E46: =1+IF(E$4>=Assumptions!$B$68,1,0) | F46: =1+IF(F$4>=Assumptions!$B$68,1,0) | G46: =1+IF(G$4>=Assumptions!$B$68,1,0) | H46: =1+IF(H$4>=Assumptions!$B$68,1,0) | I46: =1+IF(I$4>=Assumptions!$B$68,1,0) | J46: =1+IF(J$4>=Assumptions!$B$68,1,0) | ... AL46: =1+IF(AL$4>=Assumptions!$B$68,1,0)
A47: Fuel, maintenance and tires | B47: $ | C47: =C46*(Assumptions!$B$66+Assumptions!$B$67)*(1+Assumptions!$B$57)^(C$3-1) | D47: =D46*(Assumptions!$B$66+Assumptions!$B$67)*(1+Assumptions!$B$57)^(D$3-1) | E47: =E46*(Assumptions!$B$66+Assumptions!$B$67)*(1+Assumptions!$B$57)^(E$3-1) | F47: =F46*(Assumptions!$B$66+Assumptions!$B$67)*(1+Assumptions!$B$57)^(F$3-1) | G47: =G46*(Assumptions!$B$66+Assumptions!$B$67)*(1+Assumptions!$B$57)^(G$3-1) | H47: =H46*(Assumptions!$B$66+Assumptions!$B$67)*(1+Assumptions!$B$57)^(H$3-1) | I47: =I46*(Assumptions!$B$66+Assumptions!$B$67)*(1+Assumptions!$B$57)^(I$3-1) | J47: =J46*(Assumptions!$B$66+Assumptions!$B$67)*(1+Assumptions!$B$57)^(J$3-1) | ... AL47: =AL46*(Assumptions!$B$66+Assumptions!$B$67)*(1+Assumptions!$B$57)^(AL$3-1)
A48: Insurance: liability, auto, tools, umbrella | B48: $ | C48: =(Assumptions!$B$77+(C46-1)*Assumptions!$B$73/12)*(1+Assumptions!$B$57)^(C$3-1) | D48: =(Assumptions!$B$77+(D46-1)*Assumptions!$B$73/12)*(1+Assumptions!$B$57)^(D$3-1) | E48: =(Assumptions!$B$77+(E46-1)*Assumptions!$B$73/12)*(1+Assumptions!$B$57)^(E$3-1) | F48: =(Assumptions!$B$77+(F46-1)*Assumptions!$B$73/12)*(1+Assumptions!$B$57)^(F$3-1) | G48: =(Assumptions!$B$77+(G46-1)*Assumptions!$B$73/12)*(1+Assumptions!$B$57)^(G$3-1) | H48: =(Assumptions!$B$77+(H46-1)*Assumptions!$B$73/12)*(1+Assumptions!$B$57)^(H$3-1) | I48: =(Assumptions!$B$77+(I46-1)*Assumptions!$B$73/12)*(1+Assumptions!$B$57)^(I$3-1) | J48: =(Assumptions!$B$77+(J46-1)*Assumptions!$B$73/12)*(1+Assumptions!$B$57)^(J$3-1) | ... AL48: =(Assumptions!$B$77+(AL46-1)*Assumptions!$B$73/12)*(1+Assumptions!$B$57)^(AL$3-1)
A49: Workers compensation (on field payroll) | B49: $ | C49: =(C40/1.15)*Assumptions!$B$74 | D49: =(D40/1.15)*Assumptions!$B$74 | E49: =(E40/1.15)*Assumptions!$B$74 | F49: =(F40/1.15)*Assumptions!$B$74 | G49: =(G40/1.15)*Assumptions!$B$74 | H49: =(H40/1.15)*Assumptions!$B$74 | I49: =(I40/1.15)*Assumptions!$B$74 | J49: =(J40/1.15)*Assumptions!$B$74 | ... AL49: =(AL40/1.15)*Assumptions!$B$74
A50: Marketing | B50: $ | C50: =IF(C$3=1,INDEX(Assumptions!$C$81:$N$81,1,C$4),IF(C$3=2,C20*Assumptions!$B$82,C20*Assumptions!$B$83)) | D50: =IF(D$3=1,INDEX(Assumptions!$C$81:$N$81,1,D$4),IF(D$3=2,D20*Assumptions!$B$82,D20*Assumptions!$B$83)) | E50: =IF(E$3=1,INDEX(Assumptions!$C$81:$N$81,1,E$4),IF(E$3=2,E20*Assumptions!$B$82,E20*Assumptions!$B$83)) | F50: =IF(F$3=1,INDEX(Assumptions!$C$81:$N$81,1,F$4),IF(F$3=2,F20*Assumptions!$B$82,F20*Assumptions!$B$83)) | G50: =IF(G$3=1,INDEX(Assumptions!$C$81:$N$81,1,G$4),IF(G$3=2,G20*Assumptions!$B$82,G20*Assumptions!$B$83)) | H50: =IF(H$3=1,INDEX(Assumptions!$C$81:$N$81,1,H$4),IF(H$3=2,H20*Assumptions!$B$82,H20*Assumptions!$B$83)) | I50: =IF(I$3=1,INDEX(Assumptions!$C$81:$N$81,1,I$4),IF(I$3=2,I20*Assumptions!$B$82,I20*Assumptions!$B$83)) | J50: =IF(J$3=1,INDEX(Assumptions!$C$81:$N$81,1,J$4),IF(J$3=2,J20*Assumptions!$B$82,J20*Assumptions!$B$83)) | ... AL50: =IF(AL$3=1,INDEX(Assumptions!$C$81:$N$81,1,AL$4),IF(AL$3=2,AL20*Assumptions!$B$82,AL20*Assumptions!$B$83))
A51: Card and bank fees | B51: $ | C51: =C20*Assumptions!$B$87 | D51: =D20*Assumptions!$B$87 | E51: =E20*Assumptions!$B$87 | F51: =F20*Assumptions!$B$87 | G51: =G20*Assumptions!$B$87 | H51: =H20*Assumptions!$B$87 | I51: =I20*Assumptions!$B$87 | J51: =J20*Assumptions!$B$87 | ... AL51: =AL20*Assumptions!$B$87
A52: Depreciation (vans) | B52: $ | C52: =C46*Assumptions!$B$65 | D52: =D46*Assumptions!$B$65 | E52: =E46*Assumptions!$B$65 | F52: =F46*Assumptions!$B$65 | G52: =G46*Assumptions!$B$65 | H52: =H46*Assumptions!$B$65 | I52: =I46*Assumptions!$B$65 | J52: =J46*Assumptions!$B$65 | ... AL52: =AL46*Assumptions!$B$65
A53: Interest on van loans | B53: $ | C53: =-IPMT(Assumptions!$B$62/12,C$4,Assumptions!$B$63,Assumptions!$B$60-Assumptions!$B$61)*IF(C$4<=Assumptions!$B$63,1,0)-IF(C$4>=Assumptions!$B$68,IPMT(Assumptions!$B$62/12,C$4-Assumptions!$B$68+1,Assumptions!$B$63,Assumptions!$B$60-Assumptions!$B$61),0) | D53: =-IPMT(Assumptions!$B$62/12,D$4,Assumptions!$B$63,Assumptions!$B$60-Assumptions!$B$61)*IF(D$4<=Assumptions!$B$63,1,0)-IF(D$4>=Assumptions!$B$68,IPMT(Assumptions!$B$62/12,D$4-Assumptions!$B$68+1,Assumptions!$B$63,Assumptions!$B$60-Assumptions!$B$61),0) | E53: =-IPMT(Assumptions!$B$62/12,E$4,Assumptions!$B$63,Assumptions!$B$60-Assumptions!$B$61)*IF(E$4<=Assumptions!$B$63,1,0)-IF(E$4>=Assumptions!$B$68,IPMT(Assumptions!$B$62/12,E$4-Assumptions!$B$68+1,Assumptions!$B$63,Assumptions!$B$60-Assumptions!$B$61),0) | F53: =-IPMT(Assumptions!$B$62/12,F$4,Assumptions!$B$63,Assumptions!$B$60-Assumptions!$B$61)*IF(F$4<=Assumptions!$B$63,1,0)-IF(F$4>=Assumptions!$B$68,IPMT(Assumptions!$B$62/12,F$4-Assumptions!$B$68+1,Assumptions!$B$63,Assumptions!$B$60-Assumptions!$B$61),0) | G53: =-IPMT(Assumptions!$B$62/12,G$4,Assumptions!$B$63,Assumptions!$B$60-Assumptions!$B$61)*IF(G$4<=Assumptions!$B$63,1,0)-IF(G$4>=Assumptions!$B$68,IPMT(Assumptions!$B$62/12,G$4-Assumptions!$B$68+1,Assumptions!$B$63,Assumptions!$B$60-Assumptions!$B$61),0) | H53: =-IPMT(Assumptions!$B$62/12,H$4,Assumptions!$B$63,Assumptions!$B$60-Assumptions!$B$61)*IF(H$4<=Assumptions!$B$63,1,0)-IF(H$4>=Assumptions!$B$68,IPMT(Assumptions!$B$62/12,H$4-Assumptions!$B$68+1,Assumptions!$B$63,Assumptions!$B$60-Assumptions!$B$61),0) | I53: =-IPMT(Assumptions!$B$62/12,I$4,Assumptions!$B$63,Assumptions!$B$60-Assumptions!$B$61)*IF(I$4<=Assumptions!$B$63,1,0)-IF(I$4>=Assumptions!$B$68,IPMT(Assumptions!$B$62/12,I$4-Assumptions!$B$68+1,Assumptions!$B$63,Assumptions!$B$60-Assumptions!$B$61),0) | J53: =-IPMT(Assumptions!$B$62/12,J$4,Assumptions!$B$63,Assumptions!$B$60-Assumptions!$B$61)*IF(J$4<=Assumptions!$B$63,1,0)-IF(J$4>=Assumptions!$B$68,IPMT(Assumptions!$B$62/12,J$4-Assumptions!$B$68+1,Assumptions!$B$63,Assumptions!$B$60-Assumptions!$B$61),0) | ... AL53: =-IPMT(Assumptions!$B$62/12,AL$4,Assumptions!$B$63,Assumptions!$B$60-Assumptions!$B$61)*IF(AL$4<=Assumptions!$B$63,1,0)-IF(AL$4>=Assumptions!$B$68,IPMT(Assumptions!$B$62/12,AL$4-Assumptions!$B$68+1,Assumptions!$B$63,Assumptions!$B$60-Assumptions!$B$61),0)
A54: Total operating expenses | B54: $ | C54: =SUM(C44:C45)+SUM(C47:C53) | D54: =SUM(D44:D45)+SUM(D47:D53) | E54: =SUM(E44:E45)+SUM(E47:E53) | F54: =SUM(F44:F45)+SUM(F47:F53) | G54: =SUM(G44:G45)+SUM(G47:G53) | H54: =SUM(H44:H45)+SUM(H47:H53) | I54: =SUM(I44:I45)+SUM(I47:I53) | J54: =SUM(J44:J45)+SUM(J47:J53) | ... AL54: =SUM(AL44:AL45)+SUM(AL47:AL53)
A55: Operating profit before owner compensation | B55: $ | C55: =C41-C54 | D55: =D41-D54 | E55: =E41-E54 | F55: =F41-F54 | G55: =G41-G54 | H55: =H41-H54 | I55: =I41-I54 | J55: =J41-J54 | ... AL55: =AL41-AL54
A56: Owner draw (salary) | B56: $ | C56: =IF(C$3=1,IF(C$4<=3,Assumptions!$B$37,IF(C$4<=6,Assumptions!$B$38,Assumptions!$B$39)),IF(C$3=2,Assumptions!$B$40,Assumptions!$B$41)) | D56: =IF(D$3=1,IF(D$4<=3,Assumptions!$B$37,IF(D$4<=6,Assumptions!$B$38,Assumptions!$B$39)),IF(D$3=2,Assumptions!$B$40,Assumptions!$B$41)) | E56: =IF(E$3=1,IF(E$4<=3,Assumptions!$B$37,IF(E$4<=6,Assumptions!$B$38,Assumptions!$B$39)),IF(E$3=2,Assumptions!$B$40,Assumptions!$B$41)) | F56: =IF(F$3=1,IF(F$4<=3,Assumptions!$B$37,IF(F$4<=6,Assumptions!$B$38,Assumptions!$B$39)),IF(F$3=2,Assumptions!$B$40,Assumptions!$B$41)) | G56: =IF(G$3=1,IF(G$4<=3,Assumptions!$B$37,IF(G$4<=6,Assumptions!$B$38,Assumptions!$B$39)),IF(G$3=2,Assumptions!$B$40,Assumptions!$B$41)) | H56: =IF(H$3=1,IF(H$4<=3,Assumptions!$B$37,IF(H$4<=6,Assumptions!$B$38,Assumptions!$B$39)),IF(H$3=2,Assumptions!$B$40,Assumptions!$B$41)) | I56: =IF(I$3=1,IF(I$4<=3,Assumptions!$B$37,IF(I$4<=6,Assumptions!$B$38,Assumptions!$B$39)),IF(I$3=2,Assumptions!$B$40,Assumptions!$B$41)) | J56: =IF(J$3=1,IF(J$4<=3,Assumptions!$B$37,IF(J$4<=6,Assumptions!$B$38,Assumptions!$B$39)),IF(J$3=2,Assumptions!$B$40,Assumptions!$B$41)) | ... AL56: =IF(AL$3=1,IF(AL$4<=3,Assumptions!$B$37,IF(AL$4<=6,Assumptions!$B$38,Assumptions!$B$39)),IF(AL$3=2,Assumptions!$B$40,Assumptions!$B$41))
A57: Net profit before tax | B57: $ | C57: =C55-C56 | D57: =D55-D56 | E57: =E55-E56 | F57: =F55-F56 | G57: =G55-G56 | H57: =H55-H56 | I57: =I55-I56 | J57: =J55-J56 | ... AL57: =AL55-AL56
A58: Net margin | B58: % | C58: =IF(C20=0,0,C57/C20) | D58: =IF(D20=0,0,D57/D20) | E58: =IF(E20=0,0,E57/E20) | F58: =IF(F20=0,0,F57/F20) | G58: =IF(G20=0,0,G57/G20) | H58: =IF(H20=0,0,H57/H20) | I58: =IF(I20=0,0,I57/I20) | J58: =IF(J20=0,0,J57/J20) | ... AL58: =IF(AL20=0,0,AL57/AL20)
A60: Cash flow
A61: Collections from customers | B61: $ | C61: =C20*Assumptions!$B$88 | D61: =D20*Assumptions!$B$88+C20*Assumptions!$B$89 | E61: =E20*Assumptions!$B$88+D20*Assumptions!$B$89 | F61: =F20*Assumptions!$B$88+E20*Assumptions!$B$89 | G61: =G20*Assumptions!$B$88+F20*Assumptions!$B$89 | H61: =H20*Assumptions!$B$88+G20*Assumptions!$B$89 | I61: =I20*Assumptions!$B$88+H20*Assumptions!$B$89 | J61: =J20*Assumptions!$B$88+I20*Assumptions!$B$89 | K61: =K20*Assumptions!$B$88+J20*Assumptions!$B$89 | ... AL61: =AL20*Assumptions!$B$88+AK20*Assumptions!$B$89
A62: Materials, equipment and subs paid | B62: $ | C62: =C32 | D62: =D32 | E62: =E32 | F62: =F32 | G62: =G32 | H62: =H32 | I62: =I32 | J62: =J32 | ... AL62: =AL32
A63: Field labor paid | B63: $ | C63: =C40 | D63: =D40 | E63: =E40 | F63: =F40 | G63: =G40 | H63: =H40 | I63: =I40 | J63: =J40 | ... AL63: =AL40
A64: Operating expenses paid (excluding depreciation and interest) | B64: $ | C64: =C54-C52-C53 | D64: =D54-D52-D53 | E64: =E54-E52-E53 | F64: =F54-F52-F53 | G64: =G54-G52-G53 | H64: =H54-H52-H53 | I64: =I54-I52-I53 | J64: =J54-J52-J53 | ... AL64: =AL54-AL52-AL53
A65: Van loan payments (principal and interest) | B65: $ | C65: =Assumptions!$B$64*IF(C$4<=Assumptions!$B$63,1,0)+IF(C$4>=Assumptions!$B$68,Assumptions!$B$64,0) | D65: =Assumptions!$B$64*IF(D$4<=Assumptions!$B$63,1,0)+IF(D$4>=Assumptions!$B$68,Assumptions!$B$64,0) | E65: =Assumptions!$B$64*IF(E$4<=Assumptions!$B$63,1,0)+IF(E$4>=Assumptions!$B$68,Assumptions!$B$64,0) | F65: =Assumptions!$B$64*IF(F$4<=Assumptions!$B$63,1,0)+IF(F$4>=Assumptions!$B$68,Assumptions!$B$64,0) | G65: =Assumptions!$B$64*IF(G$4<=Assumptions!$B$63,1,0)+IF(G$4>=Assumptions!$B$68,Assumptions!$B$64,0) | H65: =Assumptions!$B$64*IF(H$4<=Assumptions!$B$63,1,0)+IF(H$4>=Assumptions!$B$68,Assumptions!$B$64,0) | I65: =Assumptions!$B$64*IF(I$4<=Assumptions!$B$63,1,0)+IF(I$4>=Assumptions!$B$68,Assumptions!$B$64,0) | J65: =Assumptions!$B$64*IF(J$4<=Assumptions!$B$63,1,0)+IF(J$4>=Assumptions!$B$68,Assumptions!$B$64,0) | ... AL65: =Assumptions!$B$64*IF(AL$4<=Assumptions!$B$63,1,0)+IF(AL$4>=Assumptions!$B$68,Assumptions!$B$64,0)
A66: Van 2 down payment | B66: $ | C66: =IF(C$4=Assumptions!$B$68,Assumptions!$B$61,0) | D66: =IF(D$4=Assumptions!$B$68,Assumptions!$B$61,0) | E66: =IF(E$4=Assumptions!$B$68,Assumptions!$B$61,0) | F66: =IF(F$4=Assumptions!$B$68,Assumptions!$B$61,0) | G66: =IF(G$4=Assumptions!$B$68,Assumptions!$B$61,0) | H66: =IF(H$4=Assumptions!$B$68,Assumptions!$B$61,0) | I66: =IF(I$4=Assumptions!$B$68,Assumptions!$B$61,0) | J66: =IF(J$4=Assumptions!$B$68,Assumptions!$B$61,0) | ... AL66: =IF(AL$4=Assumptions!$B$68,Assumptions!$B$61,0)
A67: Owner draw | B67: $ | C67: =C56 | D67: =D56 | E67: =E56 | F67: =F56 | G67: =G56 | H67: =H56 | I67: =I56 | J67: =J56 | ... AL67: =AL56
A68: Net cash flow | B68: $ | C68: =C61-C62-C63-C64-C65-C66-C67 | D68: =D61-D62-D63-D64-D65-D66-D67 | E68: =E61-E62-E63-E64-E65-E66-E67 | F68: =F61-F62-F63-F64-F65-F66-F67 | G68: =G61-G62-G63-G64-G65-G66-G67 | H68: =H61-H62-H63-H64-H65-H66-H67 | I68: =I61-I62-I63-I64-I65-I66-I67 | J68: =J61-J62-J63-J64-J65-J66-J67 | ... AL68: =AL61-AL62-AL63-AL64-AL65-AL66-AL67
A69: Opening cash | B69: $ | C69: ='Startup Costs'!$D$21 | D69: =C70 | E69: =D70 | F69: =E70 | G69: =F70 | H69: =G70 | I69: =H70 | J69: =I70 | K69: =J70 | ... AL69: =AK70
A70: Ending cash | B70: $ | C70: =C69+C68 | D70: =D69+D68 | E70: =E69+E68 | F70: =F69+F68 | G70: =G69+G68 | H70: =H69+H68 | I70: =I69+I68 | J70: =J69+J68 | ... AL70: =AL69+AL68
